skpomade/__init__.py
skpomade/_dev_range_approximation.py
skpomade/factorization_construction.py
skpomade/range_approximation.py
skpomade/utils.py
skpomade/tests/__init__.py
skpomade/tests/test_dev_range_approximation.py
skpomade/tests/test_factorization_construction.py
skpomade/tests/test_range_approximation.py
skpomade/tests/test_utils.py
skpomade-0.1.4.dist-info/DESCRIPTION.rst
skpomade-0.1.4.dist-info/METADATA
skpomade-0.1.4.dist-info/RECORD
skpomade-0.1.4.dist-info/WHEEL
skpomade-0.1.4.dist-info/metadata.json
skpomade-0.1.4.dist-info/top_level.txt
