Metadata-Version: 2.0
Name: skpomade
Version: 0.1.4
Summary: PrObabilistic MAtrix DEcompositions from Halko et al., 2011
Home-page: https://gitlab.lis-lab.fr/valentin.emiya/skpomade
Author: Valentin Emiya
Author-email: valentin.emiya@lis-lab.fr
License: GNU General Public License v3 (GPLv3)
Keywords: matrix,decomposition,randomized,probabilistic,algorithm
Platform: UNKNOWN
Classifier: Development Status :: 5 - Production/Stable
Classifier: Intended Audience :: Developers
Classifier: Intended Audience :: End Users/Desktop
Classifier: Intended Audience :: Science/Research
Classifier: Topic :: Scientific/Engineering :: Mathematics
Classifier: License :: OSI Approved :: GNU General Public License v3 (GPLv3)
Classifier: Natural Language :: English
Classifier: Operating System :: MacOS :: MacOS X 
Classifier: Operating System :: POSIX :: Linux
Classifier: Programming Language :: Python :: 3.6
Requires-Python: >=3.6
Requires-Dist: numpy
Requires-Dist: scipy
Provides-Extra: dev
Requires-Dist: coverage; extra == 'dev'
Requires-Dist: pytest; extra == 'dev'
Requires-Dist: pytest-cov; extra == 'dev'
Requires-Dist: pytest-randomly; extra == 'dev'
Provides-Extra: doc
Requires-Dist: nbsphinx; extra == 'doc'
Requires-Dist: numpydoc; extra == 'doc'
Requires-Dist: sphinx; extra == 'doc'
